storms/__init__.py
storms/_datasource.py
storms/_utils.py
storms/py.typed
storms/precip/__init__.py
storms/precip/_dashboard.py
storms/precip/_disagg.py
storms/precip/_rainrank.py
storms/precip/eva.py
storms/precip/hdsc-nws-noaa-gov-chain.pem
storms/precip/index.html
storms/precip/network.py
storms/precip/raingage.py
storms/precip/datasets/Logan.1h
storms/precip/datasets/__init__.py
storms/precip/datasets/_asos.py
storms/precip/datasets/_asos_http.py
storms/precip/datasets/_globalhourly.py
storms/precip/datasets/_nexrad.py
storms/precip/datasets/_nexradmaps.py
storms/precip/datasets/isd_history.txt
storms/tide/__init__.py
storms/tide/datasets/__init__.py
storms/tide/datasets/_noaa.py
storms-1.2.4.dist-info/METADATA
storms-1.2.4.dist-info/WHEEL
storms-1.2.4.dist-info/licenses/LICENSE
storms-1.2.4.dist-info/RECORD
