Metadata-Version: 2.4
Name: storms
Version: 1.2.4
Summary: Python water data and statistics library
Project-URL: Homepage, https://github.com/karosc/storms
Project-URL: Documentation, https://karosc/storms
Author-email: Constantine Karos <ckaros@outlook.com>
License-Expression: GPL-3.0-only
License-File: LICENSE
Keywords: storms
Classifier: Development Status :: 2 - Pre-Alpha
Classifier: Intended Audience :: Developers
Classifier: License :: OSI Approved :: GNU General Public License v3 (GPLv3)
Classifier: Natural Language :: English
Classifier: Programming Language :: Python :: 3
Classifier: Programming Language :: Python :: 3.7
Classifier: Programming Language :: Python :: 3.8
Classifier: Programming Language :: Python :: 3.9
Classifier: Programming Language :: Python :: 3.10
Classifier: Programming Language :: Python :: 3.11
Requires-Python: >=3.10
Requires-Dist: aiohttp
Requires-Dist: aiohttp-retry
Requires-Dist: jinja2
Requires-Dist: lmoments3>=1.0.5
Requires-Dist: numba>=0.61.2
Requires-Dist: numpy>=2
Requires-Dist: pandas>=2
Requires-Dist: pillow
Requires-Dist: pyproj
Requires-Dist: requests
Requires-Dist: scipy
Requires-Dist: shapely
Requires-Dist: tqdm
